LICENSE
MANIFEST.in
README.rst
requirements.txt
setup.py
test_sitemap.py
apsitemap/__init__.py
apsitemap/main.py
apsitemap/spider.py
apsitemap/urlset.py
apsitemap/utility.py
apsitemap.egg-info/PKG-INFO
apsitemap.egg-info/SOURCES.txt
apsitemap.egg-info/dependency_links.txt
apsitemap.egg-info/entry_points.txt
apsitemap.egg-info/requires.txt
apsitemap.egg-info/top_level.txt