Metadata-Version: 1.1
Name: apsitemap
Version: 0.2.3
Summary: python3 website sitemap generator tool!
Home-page: https://github.com/gamelife1314/sitemap
Author: Gamelife
Author-email: fudenglong1417@gmail.com
License: MIT
Platform: all
Classifier: Development Status :: 4 - Beta
Classifier: Intended Audience :: Developers
Classifier: Programming Language :: Python :: 3.5
